cve_analyzer/__init__.py
cve_analyzer/analyzer.py
cve_analyzer/dataset/dataset.json
cve_analyzer/model/meta.json
cve_analyzer/model/tokenizer
cve_analyzer/model/ner/cfg
cve_analyzer/model/ner/lower_model
cve_analyzer/model/ner/moves
cve_analyzer/model/ner/tok2vec_model
cve_analyzer/model/ner/upper_model
cve_analyzer/model/vocab/key2row
cve_analyzer/model/vocab/lexemes.bin
cve_analyzer/model/vocab/strings.json
cve_analyzer/model/vocab/vectors
cve_analyzer-0.0.4.dist-info/METADATA
cve_analyzer-0.0.4.dist-info/WHEEL
cve_analyzer-0.0.4.dist-info/top_level.txt
cve_analyzer-0.0.4.dist-info/RECORD
