Metadata-Version: 2.1
Name: cve-analyzer
Version: 0.0.4
Summary: Simple package that given a CVE desription tries to extract useful semantics from it using NLP
Home-page: https://github.com/Phat3/CVE-analyzer
Author: Sebastiano Mariani
Author-email: mariani.sebastiano@gmail.com
License: UNKNOWN
Platform: UNKNOWN
Requires-Dist: spacy (==2.0.18)
